README.rst
setup.py
pyCESM/__init__.py
pyCESM/cam_diag.py
pyCESM/kernel.py
pyCESM/physconst.py
pyCESM/shr_const_mod.py
pyCESM/wv_sat_methods.py
pyCESM/wv_saturation.py
pyCESM.egg-info/PKG-INFO
pyCESM.egg-info/SOURCES.txt
pyCESM.egg-info/dependency_links.txt
pyCESM.egg-info/not-zip-safe
pyCESM.egg-info/requires.txt
pyCESM.egg-info/top_level.txt