Metadata-Version: 1.1
Name: pyCESM
Version: 0.3.0
Summary: Package for interactive work with the Community Earth System Model
Home-page: http://github.com/brian-rose/pyCESM
Author: Brian E. J. Rose
Author-email: brose@albany.edu
License: MIT
Keywords: climate modeling modelling model gcm
Platform: UNKNOWN
Classifier: Development Status :: 3 - Alpha
Classifier: License :: OSI Approved :: MIT License
Classifier: Programming Language :: Python :: 2.7
Classifier: Programming Language :: Python :: 3.6
Classifier: Intended Audience :: Education
Classifier: Intended Audience :: Science/Research
Classifier: Topic :: Scientific/Engineering :: Atmospheric Science
